Metadata-Version: 2.1
Name: hashflow-python
Version: 10.7.0
Summary: Python SDK to interact with hashflow Smart Contracts
Home-page: UNKNOWN
Author: H-Protocol Inc
Author-email: varun@hashflow.com
License: Apache 2.0
Keywords: hashflow exchange api defi ethereum eth
Platform: UNKNOWN
Requires-Dist: web3 (==5.26.0)
Requires-Dist: eth-account
Requires-Dist: setuptools (==56.0.0)
Requires-Dist: eth-keys
